borders/__init__.py
borders/borders.py
borders/ex03.py
borders/ex04.py
borders/ex99.py
borders-1.3.0.post1.dist-info/licenses/LICENSE.md
borders-1.3.0.post1.dist-info/METADATA
borders-1.3.0.post1.dist-info/WHEEL
borders-1.3.0.post1.dist-info/top_level.txt
borders-1.3.0.post1.dist-info/RECORD
