Metadata-Version: 2.4
Name: borders
Version: 1.3.0.post1
Summary: A module to create a frame when printing a list of strings, with control on the alignment of the text and frame. Can also act like 'input()'.
Author-email: scalvaruso <calvaruso.simone@gmail.com>
License: MIT License
Project-URL: Homepage, https://pypi.org/project/borders/
Project-URL: Repository, https://github.com/scalvaruso/borders
Project-URL: Issues, https://github.com/scalvaruso/borders/issues
Keywords: alignment,break,center,centre,color,format,frame,highlight,input,left,line,output,right,split,text
Classifier: Programming Language :: Python :: 3
Classifier: Programming Language :: Python :: 3.9
Classifier: Programming Language :: Python :: 3.10
Classifier: Programming Language :: Python :: 3.11
Classifier: License :: OSI Approved :: MIT License
Classifier: Operating System :: OS Independent
Requires-Python: >=3.9
License-File: LICENSE.md
Requires-Dist: polychromy>=1.1.1
Requires-Dist: textlinebreaker>=1.0.0
Provides-Extra: windows
Requires-Dist: colorama>=0.4.6; extra == "windows"
Provides-Extra: dev
Requires-Dist: pytest>=7.0; extra == "dev"
Requires-Dist: black>=23.0; extra == "dev"
Requires-Dist: twine>=4.0; extra == "dev"
Dynamic: license-file
